kick_mcpserver-0.1.0.dist-info/licenses/LICENSE
mcpserver_init/__init__.py
mcpserver_init/scaffolder.py
kick_mcpserver-0.1.0.dist-info/METADATA
kick_mcpserver-0.1.0.dist-info/WHEEL
kick_mcpserver-0.1.0.dist-info/entry_points.txt
kick_mcpserver-0.1.0.dist-info/top_level.txt
kick_mcpserver-0.1.0.dist-info/RECORD
