Metadata-Version: 2.4
Name: kick-mcpserver
Version: 0.1.0
Summary: A CLI tool to scaffold an MCP server project
Author: Manoj
Classifier: Programming Language :: Python :: 3
Classifier: License :: OSI Approved :: MIT License
Classifier: Operating System :: OS Independent
Requires-Python: >=3.6
License-File: LICENSE
Dynamic: author
Dynamic: classifier
Dynamic: description
Dynamic: description-content-type
Dynamic: license-file
Dynamic: requires-python
Dynamic: summary
